LICENSE.txt
MANIFEST.in
README.md
setup.py
/Users/C5356105/Documents/repo/test/confluent-kafka-python-master/LICENSE.txt
/Users/C5356105/Documents/repo/test/confluent-kafka-python-master/src/confluent_kafka/src/Admin.c
/Users/C5356105/Documents/repo/test/confluent-kafka-python-master/src/confluent_kafka/src/AdminTypes.c
/Users/C5356105/Documents/repo/test/confluent-kafka-python-master/src/confluent_kafka/src/Consumer.c
/Users/C5356105/Documents/repo/test/confluent-kafka-python-master/src/confluent_kafka/src/Metadata.c
/Users/C5356105/Documents/repo/test/confluent-kafka-python-master/src/confluent_kafka/src/Producer.c
/Users/C5356105/Documents/repo/test/confluent-kafka-python-master/src/confluent_kafka/src/confluent_kafka.c
src/confluent_kafka/__init__.py
src/confluent_kafka/deserializing_consumer.py
src/confluent_kafka/error.py
src/confluent_kafka/serializing_producer.py
src/confluent_kafka/admin/__init__.py
src/confluent_kafka/admin/_acl.py
src/confluent_kafka/admin/_config.py
src/confluent_kafka/admin/_resource.py
src/confluent_kafka/avro/__init__.py
src/confluent_kafka/avro/cached_schema_registry_client.py
src/confluent_kafka/avro/error.py
src/confluent_kafka/avro/load.py
src/confluent_kafka/avro/serializer/__init__.py
src/confluent_kafka/avro/serializer/message_serializer.py
src/confluent_kafka/kafkatest/__init__.py
src/confluent_kafka/kafkatest/verifiable_client.py
src/confluent_kafka/kafkatest/verifiable_consumer.py
src/confluent_kafka/kafkatest/verifiable_producer.py
src/confluent_kafka/schema_registry/__init__.py
src/confluent_kafka/schema_registry/avro.py
src/confluent_kafka/schema_registry/error.py
src/confluent_kafka/schema_registry/json_schema.py
src/confluent_kafka/schema_registry/protobuf.py
src/confluent_kafka/schema_registry/schema_registry_client.py
src/confluent_kafka/serialization/__init__.py
src/confluent_kafka/src/Admin.c
src/confluent_kafka/src/AdminTypes.c
src/confluent_kafka/src/Consumer.c
src/confluent_kafka/src/Metadata.c
src/confluent_kafka_pypy.egg-info/PKG-INFO
src/confluent_kafka_pypy.egg-info/SOURCES.txt
src/confluent_kafka_pypy.egg-info/dependency_links.txt
src/confluent_kafka_pypy.egg-info/requires.txt
src/confluent_kafka_pypy.egg-info/top_level.txt