Metadata-Version: 2.1
Name: confluent-kafka-pypy
Version: 1.9.2
Summary: Confluent's Python client for Apache Kafka
Home-page: https://github.com/confluentinc/confluent-kafka-python
Author: Confluent Inc
Author-email: support@confluent.io
Classifier: Development Status :: 5 - Production/Stable
Classifier: Intended Audience :: Developers
Classifier: License :: OSI Approved :: Apache Software License
Classifier: Programming Language :: Python
Classifier: Programming Language :: Python :: 2.7
Classifier: Programming Language :: Python :: 3
Classifier: Topic :: Software Development :: Libraries :: Python Modules
Provides-Extra: schema-registry
Provides-Extra: avro
Provides-Extra: json
Provides-Extra: protobuf
Provides-Extra: dev
Provides-Extra: doc
License-File: LICENSE.txt
